iohgnbg/__init__.py
iohgnbg/gnbg_base.py
iohgnbg/gnbg_problem.py
iohgnbg-0.0.1.dist-info/METADATA
iohgnbg-0.0.1.dist-info/WHEEL
iohgnbg-0.0.1.dist-info/top_level.txt
iohgnbg-0.0.1.dist-info/RECORD
